Metadata-Version: 2.1
Name: StrangeSerializer-for-lab-3
Version: 1.0
Summary: Serializer for lab_3
Author: Mihail Kornievich
Classifier: Intended Audience :: Developers
Classifier: Programming Language :: Python :: 3.10
Classifier: Operating System :: OS Independent
